task_dispatcher/__init__.py
task_dispatcher/__main__.py
task_dispatcher/apps.py
task_dispatcher/celery.py
task_dispatcher/commands.py
task_dispatcher/decorators.py
task_dispatcher/register.py
task_dispatcher/settings.py
task_dispatcher/management/__init__.py
task_dispatcher/management/commands/__init__.py
task_dispatcher/management/commands/task_dispatcher.py
task_dispatcher-1.4.5.dist-info/DESCRIPTION.rst
task_dispatcher-1.4.5.dist-info/LICENSE.txt
task_dispatcher-1.4.5.dist-info/METADATA
task_dispatcher-1.4.5.dist-info/RECORD
task_dispatcher-1.4.5.dist-info/WHEEL
task_dispatcher-1.4.5.dist-info/entry_points.txt
task_dispatcher-1.4.5.dist-info/metadata.json
task_dispatcher-1.4.5.dist-info/top_level.txt
