Metadata-Version: 2.0
Name: task-dispatcher
Version: 1.4.5
Summary: Library that provides a system to generate tasks producers and consumers with ease.
Home-page: https://github.com/PeRDy/task-dispatcher
Author: José Antonio Perdiguero López
Author-email: perdy.hh@gmail.com
License: GPLv3
Download-URL: https://github.com/PeRDy/task-dispatcher
Keywords: python stream data dispatcher flow database cache celery producer consumer scheduler
Platform: UNKNOWN
Classifier: Development Status :: 5 - Production/Stable
Classifier: Intended Audience :: Developers
Classifier: License :: OSI Approved :: GNU General Public License v3 (GPLv3)
Classifier: Natural Language :: English
Classifier: Programming Language :: Python
Classifier: Programming Language :: Python :: 3
Classifier: Topic :: Software Development :: Libraries :: Python Modules
Classifier: Topic :: Software Development :: Object Brokering
Requires-Dist: Celery
Requires-Dist: clinner
Requires-Dist: pyyaml
Requires-Dist: flower
